{"openapi":"3.1.0","info":{"title":"FastAPI","version":"0.1.0"},"paths":{"/Register":{"post":{"summary":"Register User","description":"Register a new user.\n\n- Checks if the provided email or username already exists.\n- Hashes the password and stores the new user in the database.\n\nArgs:\n    user (UserRegister): Registration data (email, username, password).\n\nReturns:\n    dict: Success message.\n\nRaises:\n    HTTPException: If email or username already exists.","operationId":"register_user_Register_post","requestBody":{"content":{"application/json":{"schema":{"$ref":"#/components/schemas/UserRegister"}}},"required":true},"responses":{"200":{"description":"Successful Response","content":{"application/json":{"schema":{}}}},"422":{"description":"Validation Error","content":{"application/json":{"schema":{"$ref":"#/components/schemas/HTTPValidationError"}}}}}}},"/Login":{"post":{"summary":"Login User","operationId":"login_user_Login_post","requestBody":{"content":{"application/x-www-form-urlencoded":{"schema":{"$ref":"#/components/schemas/Body_login_user_Login_post"}}},"required":true},"responses":{"200":{"description":"Successful Response","content":{"application/json":{"schema":{}}}},"422":{"description":"Validation Error","content":{"application/json":{"schema":{"$ref":"#/components/schemas/HTTPValidationError"}}}}}}},"/me":{"get":{"summary":"View Profile","operationId":"view_profile_me_get","responses":{"200":{"description":"Successful Response","content":{"application/json":{"schema":{"$ref":"#/components/schemas/User"}}}}},"security":[{"OAuth2PasswordBearer":[]}]}},"/posts":{"get":{"summary":"List Published Posts","operationId":"list_published_posts_posts_get","parameters":[{"name":"author","in":"query","required":false,"schema":{"anyOf":[{"type":"string"},{"type":"null"}],"title":"Author"}},{"name":"tag","in":"query","required":false,"schema":{"anyOf":[{"type":"string"},{"type":"null"}],"title":"Tag"}},{"name":"page","in":"query","required":false,"schema":{"type":"integer","minimum":1,"default":1,"title":"Page"}},{"name":"limit","in":"query","required":false,"schema":{"type":"integer","maximum":100,"minimum":1,"default":10,"title":"Limit"}}],"responses":{"200":{"description":"Successful Response","content":{"application/json":{"schema":{"type":"array","items":{"$ref":"#/components/schemas/PostOut"},"title":"Response List Published Posts Posts Get"}}}},"422":{"description":"Validation Error","content":{"application/json":{"schema":{"$ref":"#/components/schemas/HTTPValidationError"}}}}}},"post":{"summary":"Createpost","operationId":"CreatePost_posts_post","security":[{"OAuth2PasswordBearer":[]}],"requestBody":{"required":true,"content":{"application/json":{"schema":{"$ref":"#/components/schemas/PostCreate"}}}},"responses":{"200":{"description":"Successful Response","content":{"application/json":{"schema":{}}}},"422":{"description":"Validation Error","content":{"application/json":{"schema":{"$ref":"#/components/schemas/HTTPValidationError"}}}}}}},"/posts/{slug}":{"get":{"summary":"Getpost","operationId":"getPost_posts__slug__get","parameters":[{"name":"slug","in":"path","required":true,"schema":{"type":"string","title":"Slug"}}],"responses":{"200":{"description":"Successful Response","content":{"application/json":{"schema":{}}}},"422":{"description":"Validation Error","content":{"application/json":{"schema":{"$ref":"#/components/schemas/HTTPValidationError"}}}}}},"put":{"summary":"Editpost","operationId":"EditPost_posts__slug__put","security":[{"OAuth2PasswordBearer":[]}],"parameters":[{"name":"slug","in":"path","required":true,"schema":{"type":"string","title":"Slug"}}],"requestBody":{"required":true,"content":{"application/json":{"schema":{"$ref":"#/components/schemas/PostUpdate"}}}},"responses":{"200":{"description":"Successful Response","content":{"application/json":{"schema":{}}}},"422":{"description":"Validation Error","content":{"application/json":{"schema":{"$ref":"#/components/schemas/HTTPValidationError"}}}}}},"post":{"summary":"Deletepost","operationId":"DeletePost_posts__slug__post","security":[{"OAuth2PasswordBearer":[]}],"parameters":[{"name":"slug","in":"path","required":true,"schema":{"type":"string","title":"Slug"}}],"requestBody":{"required":true,"content":{"application/json":{"schema":{"$ref":"#/components/schemas/PostUpdate"}}}},"responses":{"200":{"description":"Successful Response","content":{"application/json":{"schema":{}}}},"422":{"description":"Validation Error","content":{"application/json":{"schema":{"$ref":"#/components/schemas/HTTPValidationError"}}}}}}},"/me/posts":{"get":{"summary":"Get My Posts","operationId":"get_my_posts_me_posts_get","security":[{"OAuth2PasswordBearer":[]}],"parameters":[{"name":"page","in":"query","required":false,"schema":{"type":"integer","minimum":1,"default":1,"title":"Page"}},{"name":"limit","in":"query","required":false,"schema":{"type":"integer","maximum":100,"minimum":1,"default":10,"title":"Limit"}}],"responses":{"200":{"description":"Successful Response","content":{"application/json":{"schema":{}}}},"422":{"description":"Validation Error","content":{"application/json":{"schema":{"$ref":"#/components/schemas/HTTPValidationError"}}}}}}},"/posts/{post_id}/comments":{"get":{"summary":"List Comments On Post","operationId":"list_comments_on_post_posts__post_id__comments_get","parameters":[{"name":"post_id","in":"path","required":true,"schema":{"type":"string","title":"Post Id"}}],"responses":{"200":{"description":"Successful Response","content":{"application/json":{"schema":{}}}},"422":{"description":"Validation Error","content":{"application/json":{"schema":{"$ref":"#/components/schemas/HTTPValidationError"}}}}}},"post":{"summary":"Addcomments","operationId":"AddComments_posts__post_id__comments_post","security":[{"OAuth2PasswordBearer":[]}],"parameters":[{"name":"post_id","in":"path","required":true,"schema":{"type":"string","title":"Post Id"}}],"requestBody":{"required":true,"content":{"application/json":{"schema":{"$ref":"#/components/schemas/CommentsBase"}}}},"responses":{"200":{"description":"Successful Response","content":{"application/json":{"schema":{}}}},"422":{"description":"Validation Error","content":{"application/json":{"schema":{"$ref":"#/components/schemas/HTTPValidationError"}}}}}}},"/comments/{id}":{"put":{"summary":"Editcomment","operationId":"EditComment_comments__id__put","security":[{"OAuth2PasswordBearer":[]}],"parameters":[{"name":"id","in":"path","required":true,"schema":{"type":"string","title":"Id"}}],"requestBody":{"required":true,"content":{"application/json":{"schema":{"$ref":"#/components/schemas/CommentUpdate"}}}},"responses":{"200":{"description":"Successful Response","content":{"application/json":{"schema":{}}}},"422":{"description":"Validation Error","content":{"application/json":{"schema":{"$ref":"#/components/schemas/HTTPValidationError"}}}}}},"delete":{"summary":"Deletecomment","operationId":"DeleteComment_comments__id__delete","security":[{"OAuth2PasswordBearer":[]}],"parameters":[{"name":"id","in":"path","required":true,"schema":{"type":"string","title":"Id"}}],"responses":{"200":{"description":"Successful Response","content":{"application/json":{"schema":{}}}},"422":{"description":"Validation Error","content":{"application/json":{"schema":{"$ref":"#/components/schemas/HTTPValidationError"}}}}}}},"/posts/{post_id}/like":{"post":{"summary":"Likepost","operationId":"LikePost_posts__post_id__like_post","security":[{"OAuth2PasswordBearer":[]}],"parameters":[{"name":"post_id","in":"path","required":true,"schema":{"type":"string","title":"Post Id"}}],"responses":{"200":{"description":"Successful Response","content":{"application/json":{"schema":{}}}},"422":{"description":"Validation Error","content":{"application/json":{"schema":{"$ref":"#/components/schemas/HTTPValidationError"}}}}}}},"/posts/{post_id}/unlike":{"delete":{"summary":"Unlike","operationId":"Unlike_posts__post_id__unlike_delete","security":[{"OAuth2PasswordBearer":[]}],"parameters":[{"name":"post_id","in":"path","required":true,"schema":{"type":"string","title":"Post Id"}}],"responses":{"200":{"description":"Successful Response","content":{"application/json":{"schema":{}}}},"422":{"description":"Validation Error","content":{"application/json":{"schema":{"$ref":"#/components/schemas/HTTPValidationError"}}}}}}},"/posts/{post_id}/likes":{"get":{"summary":"Likecount","operationId":"LikeCount_posts__post_id__likes_get","parameters":[{"name":"post_id","in":"path","required":true,"schema":{"type":"string","title":"Post Id"}}],"responses":{"200":{"description":"Successful Response","content":{"application/json":{"schema":{}}}},"422":{"description":"Validation Error","content":{"application/json":{"schema":{"$ref":"#/components/schemas/HTTPValidationError"}}}}}}}},"components":{"schemas":{"Body_login_user_Login_post":{"properties":{"grant_type":{"anyOf":[{"type":"string","pattern":"^password$"},{"type":"null"}],"title":"Grant Type"},"username":{"type":"string","title":"Username"},"password":{"type":"string","format":"password","title":"Password"},"scope":{"type":"string","title":"Scope","default":""},"client_id":{"anyOf":[{"type":"string"},{"type":"null"}],"title":"Client Id"},"client_secret":{"anyOf":[{"type":"string"},{"type":"null"}],"format":"password","title":"Client Secret"}},"type":"object","required":["username","password"],"title":"Body_login_user_Login_post"},"CommentUpdate":{"properties":{"content":{"type":"string","title":"Content"},"created_at":{"type":"string","format":"date-time","title":"Created At"}},"type":"object","required":["content","created_at"],"title":"CommentUpdate"},"CommentsBase":{"properties":{"content":{"type":"string","title":"Content"}},"type":"object","required":["content"],"title":"CommentsBase"},"HTTPValidationError":{"properties":{"detail":{"items":{"$ref":"#/components/schemas/ValidationError"},"type":"array","title":"Detail"}},"type":"object","title":"HTTPValidationError"},"PostCreate":{"properties":{"title":{"type":"string","maxLength":100,"title":"Title"},"content":{"type":"string","title":"Content"},"tags":{"anyOf":[{"items":{"type":"string"},"type":"array"},{"type":"null"}],"title":"Tags","default":[]}},"type":"object","required":["title","content"],"title":"PostCreate"},"PostOut":{"properties":{"title":{"type":"string","maxLength":100,"title":"Title"},"content":{"type":"string","title":"Content"},"tags":{"anyOf":[{"items":{"type":"string"},"type":"array"},{"type":"null"}],"title":"Tags","default":[]},"id":{"type":"string","title":"Id"},"slug":{"type":"string","title":"Slug"},"author_name":{"type":"string","title":"Author Name"},"is_published":{"type":"boolean","title":"Is Published","default":true},"created_at":{"type":"string","format":"date-time","title":"Created At"},"updated_at":{"anyOf":[{"type":"string","format":"date-time"},{"type":"null"}],"title":"Updated At"}},"type":"object","required":["title","content","id","slug","author_name","created_at"],"title":"PostOut"},"PostUpdate":{"properties":{"title":{"anyOf":[{"type":"string"},{"type":"null"}],"title":"Title"},"content":{"anyOf":[{"type":"string"},{"type":"null"}],"title":"Content"},"tags":{"anyOf":[{"items":{"type":"string"},"type":"array"},{"type":"null"}],"title":"Tags"},"is_published":{"anyOf":[{"type":"boolean"},{"type":"null"}],"title":"Is Published"}},"type":"object","title":"PostUpdate"},"User":{"properties":{"id":{"type":"string","title":"Id"},"username":{"type":"string","title":"Username"},"email":{"type":"string","format":"email","title":"Email"},"bio":{"anyOf":[{"type":"string"},{"type":"null"}],"title":"Bio"},"created_at":{"type":"string","format":"date-time","title":"Created At"}},"type":"object","required":["id","username","email","created_at"],"title":"User"},"UserRegister":{"properties":{"username":{"type":"string","title":"Username"},"email":{"type":"string","format":"email","title":"Email"},"password":{"type":"string","title":"Password"}},"type":"object","required":["username","email","password"],"title":"UserRegister"},"ValidationError":{"properties":{"loc":{"items":{"anyOf":[{"type":"string"},{"type":"integer"}]},"type":"array","title":"Location"},"msg":{"type":"string","title":"Message"},"type":{"type":"string","title":"Error Type"}},"type":"object","required":["loc","msg","type"],"title":"ValidationError"}},"securitySchemes":{"OAuth2PasswordBearer":{"type":"oauth2","flows":{"password":{"scopes":{},"tokenUrl":"Login"}}}}}}